aouyi_develop_mcp_demo/__init__.py
aouyi_develop_mcp_demo-0.1.0.dist-info/WHEEL
aouyi_develop_mcp_demo-0.1.0.dist-info/entry_points.txt
aouyi_develop_mcp_demo-0.1.0.dist-info/METADATA
aouyi_develop_mcp_demo-0.1.0.dist-info/RECORD
